README.md
setup.cfg
setup.py
src/geometry/__init__.py
src/geometry/lingkaran.py
src/geometry/persegi.py
src/geometry/segitiga.py
src/vesty_bmkg.egg-info/PKG-INFO
src/vesty_bmkg.egg-info/SOURCES.txt
src/vesty_bmkg.egg-info/dependency_links.txt
src/vesty_bmkg.egg-info/requires.txt
src/vesty_bmkg.egg-info/top_level.txt
test/test_geometry.py