Metadata-Version: 2.1
Name: vesty-bmkg
Version: 0.0.3
Summary: tugas vesty
Home-page: https://gitlab.com/vesty/pelatihan_bmkg
Author: vesty
Author-email: vestiana.aza18@gmail.com
License: UNKNOWN
Platform: UNKNOWN
Classifier: Programming Language :: Python :: 3
Classifier: License :: OSI Approved :: MIT License
Classifier: Operating System :: OS Independent
Requires-Python: >=3.8
